volley/__init__.py
volley/concurrency.py
volley/config.py
volley/connectors/__init__.py
volley/connectors/base.py
volley/connectors/confluent.py
volley/connectors/rsmq.py
volley/connectors/zmq.py
volley/data_models.py
volley/engine.py
volley/global.yml
volley/logging.py
volley/metrics.py
volley/models/__init__.py
volley/models/base.py
volley/models/pydantic_model.py
volley/profiles.py
volley/queues.py
volley/serializers/__init__.py
volley/serializers/base.py
volley/serializers/json_serializer.py
volley/serializers/msgpack_serializer.py
volley/serializers/orjson_serializer.py
volley/transport.py
volley/util.py
py_volley-1.2.5.dist-info/LICENSE.md
py_volley-1.2.5.dist-info/METADATA
py_volley-1.2.5.dist-info/WHEEL
py_volley-1.2.5.dist-info/RECORD
