Metadata-Version: 2.1
Name: py_volley
Version: 1.2.5
Summary: Pluggable message queueing for Python
Author: Shipt
Author-email: shipt@shipt.com
Requires-Python: >=3.8.1,<4.0.0
Classifier: Programming Language :: Python :: 3
Classifier: Programming Language :: Python :: 3.9
Classifier: Programming Language :: Python :: 3.10
Classifier: Programming Language :: Python :: 3.11
Classifier: Programming Language :: Python :: 3.12
Classifier: Programming Language :: Python :: 3.13
Provides-Extra: all
Provides-Extra: kafka
Provides-Extra: rsmq
Provides-Extra: zmq
Requires-Dist: PyRSMQ (>=0.4.5,<0.5.0) ; extra == "all" or extra == "rsmq"
Requires-Dist: PyYAML (>=6.0.0,<7.0.0)
Requires-Dist: confluent-kafka (>=2.0.0,<3.0.0) ; extra == "all" or extra == "kafka"
Requires-Dist: hiredis (>=2.0,<3.0) ; extra == "all" or extra == "rsmq"
Requires-Dist: msgpack (>=1.0.3,<2.0.0)
Requires-Dist: orjson (>=3.6.4,<4.0.0)
Requires-Dist: prometheus-client (>=0,<1)
Requires-Dist: pydantic (>=2.1.0,<3.0.0)
Requires-Dist: pyzmq (>=22.3.0) ; extra == "all" or extra == "zmq"
Requires-Dist: starlette (>=0,<1)
Requires-Dist: tenacity (>=8.0.1,<9.0.0) ; extra == "all" or extra == "rsmq"
Requires-Dist: uvicorn (>=0,<1)
Project-URL: Documentation, https://github.com/shipt/py-volley/wiki
Project-URL: Homepage, https://github.com/shipt/py-volley
Project-URL: Repository, https://github.com/shipt/py-volley
